etc/novajoin/cloud-config-novajoin.json
etc/novajoin/join-api-paste.ini
novajoin/__init__.py
novajoin/base.py
novajoin/config.py
novajoin/configure_ipa.py
novajoin/context.py
novajoin/errors.py
novajoin/exception.py
novajoin/glance.py
novajoin/ipa.py
novajoin/join.py
novajoin/keystone_client.py
novajoin/middleware.py
novajoin/notifications.py
novajoin/nova.py
novajoin/policy.py
novajoin/test.py
novajoin/util.py
novajoin/wsgi.py
novajoin/middleware/__init__.py
novajoin/middleware/auth.py
novajoin/middleware/config.py
novajoin/releasenotes/notes/fix-backoff-mechanism-c681255215624413.yaml
novajoin/tests/__init__.py
novajoin/tests/functional/README
novajoin/tests/functional/__init__.py
novajoin/tests/functional/krb5.conf
novajoin/tests/functional/test_cloudinit.py
novajoin/tests/functional/test_enrollment.py
novajoin/tests/functional/test_ipa_integration.py
novajoin/tests/unit/__init__.py
novajoin/tests/unit/fake_constants.py
novajoin/tests/unit/test_service.py
novajoin/tests/unit/test_util.py
novajoin/tests/unit/api/__init__.py
novajoin/tests/unit/api/fakes.py
novajoin/tests/unit/api/v1/__init__.py
novajoin/tests/unit/api/v1/test_api.py
novajoin/tests/unit/notifications/__init__.py
novajoin/tests/unit/notifications/floatingip.update.end_associate.json
novajoin/tests/unit/notifications/floatingip.update.end_disassociate.json
novajoin/tests/unit/notifications/instance.create.end.json
novajoin/tests/unit/notifications/instance.delete.end.json
novajoin/tests/unit/notifications/instance.update.json
novajoin/tests/unit/notifications/test_formats.py
novajoin-1.3.0.data/scripts/novajoin-install
novajoin-1.3.0.data/scripts/novajoin-ipa-setup
usr/libexec/novajoin-ipa-setup
usr/share/man/man1/novajoin-install.1
usr/share/man/man1/novajoin-notify.1
usr/share/man/man1/novajoin-server.1
usr/share/novajoin/freeipa.json
usr/share/novajoin/novajoin-notify.service
usr/share/novajoin/novajoin-server.service
novajoin-1.3.0.dist-info/LICENSE
novajoin-1.3.0.dist-info/METADATA
novajoin-1.3.0.dist-info/WHEEL
novajoin-1.3.0.dist-info/entry_points.txt
novajoin-1.3.0.dist-info/pbr.json
novajoin-1.3.0.dist-info/top_level.txt
novajoin-1.3.0.dist-info/RECORD
