Metadata-Version: 2.1
Name: novajoin
Version: 1.3.0
Summary: Nova integration to enroll IPA clients
Home-page: https://github.com/openstack/novajoin
Author: Rob Crittenden
Author-email: rcritten@redhat.com
License: Apache License, Version 2.0
Platform: UNKNOWN
Classifier: Environment :: OpenStack
Classifier: Intended Audience :: Information Technology
Classifier: Intended Audience :: System Administrators
Classifier: Intended Audience :: Developers
Classifier: Topic :: Utilities
Classifier: License :: OSI Approved :: Apache Software License
Classifier: Programming Language :: Python
Classifier: Programming Language :: Python :: 2
Classifier: Programming Language :: Python :: 2.7
Classifier: Programming Language :: Python :: 3
Classifier: Programming Language :: Python :: 3.6
Classifier: Development Status :: 4 - Beta
Requires-Dist: WebOb (>=1.7.1)
Requires-Dist: Paste (>=2.0.2)
Requires-Dist: Routes (>=2.3.1)
Requires-Dist: six (>=1.10.0)
Requires-Dist: python-keystoneclient (>=3.8.0)
Requires-Dist: python-memcached (>=1.59)
Requires-Dist: keystoneauth1 (>=3.3.0)
Requires-Dist: oslo.concurrency (>=3.25.0)
Requires-Dist: oslo.config (>=6.1.0)
Requires-Dist: oslo.messaging (>=5.29.0)
Requires-Dist: oslo.policy (>=1.30.0)
Requires-Dist: oslo.serialization (!=2.19.1,>=2.18.0)
Requires-Dist: oslo.service (!=1.28.1,>=1.24.0)
Requires-Dist: oslo.utils (>=3.33.0)
Requires-Dist: python-neutronclient (>=6.3.0)
Requires-Dist: python-novaclient (>=9.1.0)
Requires-Dist: python-cinderclient (>=3.3.0)
Requires-Dist: python-glanceclient (>=2.8.0)
Requires-Dist: keystonemiddleware (>=4.17.0)
Requires-Dist: cachetools (>=2.0.0)
